_markovlv.cp312-win_amd64.pyd
markovlv.py
markovlv-2.6.0.dist-info/METADATA
markovlv-2.6.0.dist-info/WHEEL
markovlv-2.6.0.dist-info/top_level.txt
markovlv-2.6.0.dist-info/RECORD
