Metadata-Version: 2.4
Name: markovlv
Version: 2.6.0
Summary: Markov chain library with SWIG bindings
Home-page: https://docs.python.org/exteing/building
Author: Michael Koller
Author-email: Michael Koller <michael.koller@bluemail.ch>
Requires-Python: >=3.9
Dynamic: author
Dynamic: home-page
